.coveragerc
.stestr.conf
.travis.yml
AUTHORS
CHANGELOG.md
ChangeLog
LICENSE
MANIFEST.in
README.md
requirements.txt
setup.cfg
setup.py
test-requirements.txt
tox.ini
config/oneviewd-config-generator.conf
etc/ironic-oneviewd/ironic-oneviewd.conf.sample
ironic_oneviewd/__init__.py
ironic_oneviewd/exceptions.py
ironic_oneviewd/facade.py
ironic_oneviewd/manage.py
ironic_oneviewd/shell.py
ironic_oneviewd/utils.py
ironic_oneviewd.egg-info/PKG-INFO
ironic_oneviewd.egg-info/SOURCES.txt
ironic_oneviewd.egg-info/dependency_links.txt
ironic_oneviewd.egg-info/entry_points.txt
ironic_oneviewd.egg-info/not-zip-safe
ironic_oneviewd.egg-info/pbr.json
ironic_oneviewd.egg-info/requires.txt
ironic_oneviewd.egg-info/top_level.txt
ironic_oneviewd/conf/__init__.py
ironic_oneviewd/conf/default.py
ironic_oneviewd/conf/inventory.py
ironic_oneviewd/conf/oneview.py
ironic_oneviewd/conf/openstack.py
ironic_oneviewd/conf/opts.py
ironic_oneviewd/inventory_manager/__init__.py
ironic_oneviewd/inventory_manager/manage.py
ironic_oneviewd/node_manager/__init__.py
ironic_oneviewd/node_manager/manage.py
ironic_oneviewd/tests/__init__.py
ironic_oneviewd/tests/functional/__init__.py
ironic_oneviewd/tests/functional/test_ironic_oneviewd.py
ironic_oneviewd/tests/unit/__init__.py
ironic_oneviewd/tests/unit/test_utils.py