Metadata-Version: 1.1
Name: ironic-oneviewd
Version: 1.2.0
Summary: Deamon service to enroll nodes to be used for the Ironic OneView Driver
Home-page: http://git.lsd.ufcg.edu.br/ironic-drivers/ironic-oneviewd
Author: Universidade Federal de Campina Grande
Author-email: openstack@lsd.ufcg.edu.br
License: UNKNOWN
Platform: UNKNOWN
Classifier: Environment :: OpenStack
Classifier: Intended Audience :: Information Technology
Classifier: Intended Audience :: System Administrators
Classifier: License :: OSI Approved :: Apache Software License
Classifier: Operating System :: POSIX :: Linux
Classifier: Programming Language :: Python
Classifier: Programming Language :: Python :: 2
Classifier: Programming Language :: Python :: 2.7
Classifier: Programming Language :: Python :: 3
Classifier: Programming Language :: Python :: 3.3
Classifier: Programming Language :: Python :: 3.4
